lotofacil/__init__.py
lotofacil-0.0.6.dist-info/LICENSE
lotofacil-0.0.6.dist-info/METADATA
lotofacil-0.0.6.dist-info/WHEEL
lotofacil-0.0.6.dist-info/top_level.txt
lotofacil-0.0.6.dist-info/RECORD
